extract_todo/__init__.py
extract_todo/__main__.py
extract_todo/__version__.py
extract_todo/extractor.py
extract_todo/parser/__init__.py
extract_todo/parser/default_parser.py
extract_todo/parser/latex_parser.py
extract_todo/parser/parser_factory.py
extract_todo/parser/python_parser.py
extract_todo-0.3.1.dist-info/AUTHORS.md
extract_todo-0.3.1.dist-info/LICENSE.txt
extract_todo-0.3.1.dist-info/METADATA
extract_todo-0.3.1.dist-info/WHEEL
extract_todo-0.3.1.dist-info/entry_points.txt
extract_todo-0.3.1.dist-info/top_level.txt
extract_todo-0.3.1.dist-info/RECORD
