Metadata-Version: 2.1
Name: extract-todo
Version: 0.3.1
Summary: A small tool to extract TODOs
Home-page: https://github.com/follnoob/extrect-todo
Author: Jens Wilberg
Author-email: jens_wilberg@outlook.com
License: GPLv3
Project-URL: Bug Tracker, https://github.com/follnoob/extract-todo/issues
Keywords: todo,extract
Platform: UNKNOWN
Classifier: Programming Language :: Python :: 3.6
Classifier: Programming Language :: Python :: 3.7
Classifier: Programming Language :: Python :: 3.8
Classifier: Programming Language :: Python :: 3.9
Classifier: Development Status :: 5 - Production/Stable
Classifier: License :: OSI Approved :: GNU General Public License v3 (GPLv3)
Classifier: Operating System :: OS Independent
Classifier: Environment :: Console
Classifier: Intended Audience :: End Users/Desktop
Requires-Python: >=3.6
License-File: LICENSE.txt
License-File: AUTHORS.md
